README.txt
setup.py
PyTech/structure.py
PyTech.egg-info/PKG-INFO
PyTech.egg-info/SOURCES.txt
PyTech.egg-info/dependency_links.txt
PyTech.egg-info/top_level.txt