Metadata-Version: 1.0
Name: PyTech
Version: 0.6
Summary: Emulated computer, Documentation fixed.
Home-page: UNKNOWN
Author: Robert Bassett
Author-email: bassett.w.robert@gmail.com
License: UNKNOWN
Platform: UNKNOWN
